alu32.v
module alu32(
    input [31:0] a,
    input [31:0] b,
    input [3:0] alu_ctrl,
    output reg [31:0] result,
    output zero
);
    always @(*) begin
        case(alu_ctrl)
            4'b0000: result = a + b;
            4'b0001: result = a - b;
            4'b0010: result = a & b;
            4'b0011: result = a | b;
            4'b0100: result = a ^ b;
            4'b0101: result = a << b[4:0];
            4'b0110: result = a >> b[4:0];
            4'b0111: result = ($signed(a) < $signed(b)) ? 32'd1 : 32'd0;
            default: result = 32'b0;
        endcase
    end

    assign zero = (result == 32'b0);

endmodule

alu_ctrl.v
module alu_ctrl(
    input  [1:0] alu_op,
    input  [2:0] funct3,
    input        funct7,
    output reg [3:0] alu_ctrl
);

    always @(*) begin
        case(alu_op)
            2'b00: alu_ctrl = 4'b0000;
            2'b01: alu_ctrl = 4'b0001;
            2'b10: begin
                case(funct3)
                    3'b000: begin
                        if (funct7)
                            alu_ctrl = 4'b0001;
                        else
                            alu_ctrl = 4'b0000;
                    end
                    3'b111: alu_ctrl = 4'b0010;
                    3'b110: alu_ctrl = 4'b0011;
                    3'b100: alu_ctrl = 4'b0100;
                    3'b001: alu_ctrl = 4'b0101;
                    3'b101: alu_ctrl = 4'b0110;
                    3'b010: alu_ctrl = 4'b0111;
                    default: alu_ctrl = 4'b0000;
                endcase
            end
            default: alu_ctrl = 4'b0000;
        endcase
    end

endmodule

imm_gen.v
module imm_gen(
    input  [31:0] instr,
    output reg [31:0] imm
);

    wire [6:0] opcode = instr[6:0];

    always @(*) begin
        case(opcode)
            7'b0010011: // I-type (addi)
                imm = {{20{instr[31]}}, instr[31:20]};

            7'b0000011: // I-type (load)
                imm = {{20{instr[31]}}, instr[31:20]};

            7'b0100011: // S-type (store)
                imm = {{20{instr[31]}}, instr[31:25], instr[11:7]};

            7'b1100011: // B-type (branch)
                imm = {{19{instr[31]}}, instr[31], instr[7],
                        instr[30:25], instr[11:8], 1'b0};

            7'b1101111: // J-type (jal)
                imm = {{11{instr[31]}}, instr[31], instr[19:12],
                        instr[20], instr[30:21], 1'b0};

            default:
                imm = 32'b0;
        endcase
    end

endmodule

reg_file.v
module reg_file(
    input clk,
    input we,
    input [4:0] raddr1,
    input [4:0] raddr2,
    input [4:0] waddr,
    input [31:0] wdata,
    output [31:0] rdata1,
    output [31:0] rdata2
);

    reg [31:0] registers [31:0];

    integer i;
    initial begin
        for (i = 0; i < 32; i = i + 1)
            registers[i] = 32'b0;
    end

    always @(posedge clk) begin
        if (we && waddr != 5'b0)
            registers[waddr] <= wdata;
    end

    assign rdata1 = registers[raddr1];
    assign rdata2 = registers[raddr2];

endmodule

control.v
module control(
    input[6:0]opcode,
    output reg reg_write,
    output reg alu_src,
    output reg mem_read,
    output reg mem_write,
    output reg mem_to_reg,
    output reg branch,
    output reg[1:0] alu_op
);
    always @(*) begin
        case(opcode)
            7'b0110011: begin //R-type
                reg_write = 1;
                alu_src = 0;
                mem_read = 0;
                mem_write = 0;
                mem_to_reg = 0;
                branch = 0;
                alu_op = 2'b10;
            end
            7'b0010011:begin //I-type
                reg_write = 1;
                alu_src = 1;
                mem_read = 0;
                mem_write = 0;
                mem_to_reg = 0;
                branch = 0;
                alu_op = 2'b10;
            end
            7'b0000011:begin //Load
                reg_write = 1;
                alu_src = 1;
                mem_read = 1;
                mem_write = 0;
                mem_to_reg = 1;
                branch = 0;
                alu_op = 2'b00;
            end
            7'b0100011:begin //Store
                reg_write = 0;
                alu_src = 1;
                mem_read = 0;
                mem_write = 1;
                mem_to_reg = 0; //Don't care
                branch = 0;
                alu_op = 2'b00;
            end
            7'b1100011:begin //Branch
                reg_write = 0;
                alu_src = 0;
                mem_read = 0;
                mem_write = 0;
                mem_to_reg = 0; //Don't care
                branch = 1;
                alu_op = 2'b01;
            end
            default: begin
                reg_write = 0;
                alu_src = 0;
                mem_read = 0;
                mem_write = 0;
                mem_to_reg = 0;
                branch = 0;
                alu_op = 2'b00;
            end
        endcase
    end
endmodule

imem.v
module imem(
    input [31:0] addr,
    output [31:0] instr
);

    reg [31:0] mem [0:63];

    initial begin
        // addi x1, x0, 5  →  x1 = 5
        mem[0] = 32'h00500093;
        // addi x2, x0, 3  →  x2 = 3
        mem[1] = 32'h00300113;
        // add x3, x1, x2  →  x3 = 8
        mem[2] = 32'h002081B3;
        // fill rest with zeros
        mem[3] = 32'h00C00293;
        mem[4] = 32'h00520333;
        mem[5] = 32'h401303B3;
    end
    assign instr =mem[addr[31:2]];
endmodule

pc.v
module pc(
    input      clk,
    input      rst,
    input  [31:0] pc_next,
    output reg [31:0]pc_out

);
    always @(posedge clk or posedge rst) begin
        if (rst)
            pc_out <=32'b0;
        else
            pc_out <= pc_next;
    end
endmodule

cpu.v
module cpu(
    input clk,
    input rst
);

    // ─── Internal wires ───
    wire [31:0] pc_out;
    wire [31:0] pc_next;
    wire [31:0] instr;
    wire [31:0] reg_rdata1;
    wire [31:0] reg_rdata2;
    wire [31:0] imm;
    wire [31:0] alu_b;
    wire [31:0] alu_result;
    wire        alu_zero;
    wire [31:0] reg_wdata;

    // Control signals
    wire        reg_write;
    wire        alu_src;
    wire        mem_read;
    wire        mem_write;
    wire        mem_to_reg;
    wire        branch;
    wire [1:0]  alu_op;
    wire [3:0]  alu_ctrl_out;

    // ─── PC next logic ───
    wire branch_taken;
    wire [31:0] pc_plus4;
    wire [31:0] branch_target;

    assign pc_plus4      = pc_out + 32'd4;
    assign branch_target = pc_out + imm;
    assign branch_taken  = branch & alu_zero;
    assign pc_next       = branch_taken ? branch_target : pc_plus4;

    // ─── Module instantiations ───

    pc PC (
        .clk(clk),
        .rst(rst),
        .pc_next(pc_next),
        .pc_out(pc_out)
    );

    imem IMEM (
        .addr(pc_out),
        .instr(instr)
    );

    control CTRL (
        .opcode(instr[6:0]),
        .reg_write(reg_write),
        .alu_src(alu_src),
        .mem_read(mem_read),
        .mem_write(mem_write),
        .mem_to_reg(mem_to_reg),
        .branch(branch),
        .alu_op(alu_op)
    );

    reg_file RF (
        .clk(clk),
        .we(reg_write),
        .raddr1(instr[19:15]),
        .raddr2(instr[24:20]),
        .waddr(instr[11:7]),
        .wdata(reg_wdata),
        .rdata1(reg_rdata1),
        .rdata2(reg_rdata2)
    );

    imm_gen IMMGEN (
        .instr(instr),
        .imm(imm)
    );

    alu_ctrl ALUCTRL (
        .alu_op(alu_op),
        .funct3(instr[14:12]),
        .funct7(instr[30]),
        .alu_ctrl(alu_ctrl_out)
    );

    assign alu_b = alu_src ? imm : reg_rdata2;

    alu32 ALU (
        .a(reg_rdata1),
        .b(alu_b),
        .alu_ctrl(alu_ctrl_out),
        .result(alu_result),
        .zero(alu_zero)
    );

    assign reg_wdata = alu_result;

endmodule

cpu_tb.v
module cpu_tb;

    reg clk;
    reg rst;

    cpu uut (
        .clk(clk),
        .rst(rst)
    );

    initial clk = 0;
    always #5 clk = ~clk;

    initial begin
        $dumpfile("cpu_tb.vcd");
        $dumpvars(0, cpu_tb);

        rst = 1;
        #20;
        rst = 0;

        #200

        $display("Register x1 = %0d (expected 5)",  uut.RF.registers[1]);
        $display("Register x2 = %0d (expected 3)",  uut.RF.registers[2]);
        $display("Register x3 = %0d (expected 8)",  uut.RF.registers[3]);

        $finish;
    end

endmodule

cpu_tb.vcd
$date
	Fri Jun 19 17:54:22 2026
$end
$version
	Icarus Verilog
$end
$timescale
	1s
$end
$scope module cpu_tb $end
$var reg 1 ! clk $end
$var reg 1 " rst $end
$scope module uut $end
$var wire 1 # branch_taken $end
$var wire 1 ! clk $end
$var wire 32 $ reg_wdata [31:0] $end
$var wire 1 " rst $end
$var wire 1 % reg_write $end
$var wire 32 & reg_rdata2 [31:0] $end
$var wire 32 ' reg_rdata1 [31:0] $end
$var wire 32 ( pc_plus4 [31:0] $end
$var wire 32 ) pc_out [31:0] $end
$var wire 32 * pc_next [31:0] $end
$var wire 1 + mem_write $end
$var wire 1 , mem_to_reg $end
$var wire 1 - mem_read $end
$var wire 32 . instr [31:0] $end
$var wire 32 / imm [31:0] $end
$var wire 32 0 branch_target [31:0] $end
$var wire 1 1 branch $end
$var wire 1 2 alu_zero $end
$var wire 1 3 alu_src $end
$var wire 32 4 alu_result [31:0] $end
$var wire 2 5 alu_op [1:0] $end
$var wire 4 6 alu_ctrl_out [3:0] $end
$var wire 32 7 alu_b [31:0] $end
$scope module ALU $end
$var wire 32 8 b [31:0] $end
$var wire 1 2 zero $end
$var wire 4 9 alu_ctrl [3:0] $end
$var wire 32 : a [31:0] $end
$var reg 32 ; result [31:0] $end
$upscope $end
$scope module ALUCTRL $end
$var wire 3 < funct3 [2:0] $end
$var wire 1 = funct7 $end
$var wire 2 > alu_op [1:0] $end
$var reg 4 ? alu_ctrl [3:0] $end
$upscope $end
$scope module CTRL $end
$var wire 7 @ opcode [6:0] $end
$var reg 2 A alu_op [1:0] $end
$var reg 1 3 alu_src $end
$var reg 1 1 branch $end
$var reg 1 - mem_read $end
$var reg 1 , mem_to_reg $end
$var reg 1 + mem_write $end
$var reg 1 % reg_write $end
$upscope $end
$scope module IMEM $end
$var wire 32 B instr [31:0] $end
$var wire 32 C addr [31:0] $end
$upscope $end
$scope module IMMGEN $end
$var wire 32 D instr [31:0] $end
$var wire 7 E opcode [6:0] $end
$var reg 32 F imm [31:0] $end
$upscope $end
$scope module PC $end
$var wire 1 ! clk $end
$var wire 32 G pc_next [31:0] $end
$var wire 1 " rst $end
$var reg 32 H pc_out [31:0] $end
$upscope $end
$scope module RF $end
$var wire 1 ! clk $end
$var wire 5 I raddr1 [4:0] $end
$var wire 5 J raddr2 [4:0] $end
$var wire 32 K rdata1 [31:0] $end
$var wire 32 L rdata2 [31:0] $end
$var wire 5 M waddr [4:0] $end
$var wire 32 N wdata [31:0] $end
$var wire 1 % we $end
$var integer 32 O i [31:0] $end
$upscope $end
$upscope $end
$upscope $end
$enddefinitions $end
#0
$dumpvars
b100000 O
b101 N
b1 M
b0 L
b0 K
b101 J
b0 I
b0 H
b100 G
b101 F
b10011 E
b10100000000000010010011 D
b0 C
b10100000000000010010011 B
b10 A
b10011 @
b0 ?
b10 >
0=
b0 <
b101 ;
b0 :
b0 9
b101 8
b101 7
b0 6
b10 5
b101 4
13
02
01
b101 0
b101 /
b10100000000000010010011 .
0-
0,
0+
b100 *
b0 )
b100 (
b0 '
b0 &
1%
b101 $
0#
1"
0!
$end
#5
1!
#10
0!
#15
1!
#20
0!
0"
#25
b11 $
b11 N
b11 4
b11 ;
b11 7
b11 8
b11 /
b11 F
b10 M
b11 J
b1100000000000100010011 .
b1100000000000100010011 B
b1100000000000100010011 D
b1000 *
b1000 G
b111 0
b1000 (
b100 )
b100 C
b100 H
1!
#30
0!
#35
b1000 $
b1000 N
b1000 4
b1000 ;
03
b0 /
b0 F
b110011 E
b11 M
b11 &
b11 L
b10 J
b101 '
b101 :
b101 K
b1 I
b110011 @
b1000001000000110110011 .
b1000001000000110110011 B
b1000001000000110110011 D
b1100 *
b1100 G
b1000 0
b1100 (
b1000 )
b1000 C
b1000 H
1!
#40
0!
#45
12
b0 7
b0 8
b0 $
b0 N
b0 4
b0 ;
b0 5
b0 >
b0 A
0%
b0 E
b0 M
b0 &
b0 L
b0 J
b0 '
b0 :
b0 K
b0 I
b0 @
b0 .
b0 B
b0 D
b10000 *
b10000 G
b1100 0
b10000 (
b1100 )
b1100 C
b1100 H
1!
#50
0!
#55
bx 7
bx 8
x2
bx $
bx N
bx 4
bx ;
bx E
x=
bx <
bx M
bx &
bx L
bx J
bx '
bx :
bx K
bx I
bx @
bx .
bx B
bx D
b10100 *
b10100 G
b10000 0
b10100 (
b10000 )
b10000 C
b10000 H
1!
#60
0!
#65
b11000 *
b11000 G
b10100 0
b11000 (
b10100 )
b10100 C
b10100 H
1!
#70
0!
#75
b11100 *
b11100 G
b11000 0
b11100 (
b11000 )
b11000 C
b11000 H
1!
#80
0!
#85
b100000 *
b100000 G
b11100 0
b100000 (
b11100 )
b11100 C
b11100 H
1!
#90
0!
#95
b100100 *
b100100 G
b100000 0
b100100 (
b100000 )
b100000 C
b100000 H
1!
#100
0!
#105
b101000 *
b101000 G
b100100 0
b101000 (
b100100 )
b100100 C
b100100 H
1!
#110
0!
#115
b101100 *
b101100 G
b101000 0
b101100 (
b101000 )
b101000 C
b101000 H
1!
#120
0!
#125
b110000 *
b110000 G
b101100 0
b110000 (
b101100 )
b101100 C
b101100 H
1!
#130
0!
#135
b110100 *
b110100 G
b110000 0
b110100 (
b110000 )
b110000 C
b110000 H
1!
#140
0!
#145
b111000 *
b111000 G
b110100 0
b111000 (
b110100 )
b110100 C
b110100 H
1!
#150
0!
#155
b111100 *
b111100 G
b111000 0
b111100 (
b111000 )
b111000 C
b111000 H
1!
#160
0!
#165
b1000000 *
b1000000 G
b111100 0
b1000000 (
b111100 )
b111100 C
b111100 H
1!
#170
0!
#175
b1000100 *
b1000100 G
b1000000 0
b1000100 (
b1000000 )
b1000000 C
b1000000 H
1!
#180
0!
#185
b1001000 *
b1001000 G
b1000100 0
b1001000 (
b1000100 )
b1000100 C
b1000100 H
1!
#190
0!
#195
b1001100 *
b1001100 G
b1001000 0
b1001100 (
b1001000 )
b1001000 C
b1001000 H
1!
#200
0!
#205
b1010000 *
b1010000 G
b1001100 0
b1010000 (
b1001100 )
b1001100 C
b1001100 H
1!
#210
0!
#215
b1010100 *
b1010100 G
b1010000 0
b1010100 (
b1010000 )
b1010000 C
b1010000 H
1!
