pc.v
module pc(
    input      clk,
    input      rst,
    input  [31:0] pc_next,
    output reg [31:0]pc_out

);
    always @(posedge clk or posedge rst) begin
        if (rst)
            pc_out <=32'b0;
        else
            pc_out <= pc_next;
    end
endmodule

pc_tb.v
module pc_tb;
    reg     clk;
    reg     rst;
    reg  [31:0] pc_next;
    wire [31:0] pc_out;

    pc uut (
        .clk(clk),
        .rst(rst),
        .pc_next(pc_next),
        .pc_out(pc_out)
    );
    initial clk = 0;
    always #5 clk = ~clk;

    initial begin
        $dumpfile("pc_tb.vcd");
        $dumpvars(0, pc_tb);

        rst = 1; pc_next = 0;
        #10;
        rst = 0;

        pc_next = 32'd4;
        #10;
        $display("PC = %0d (expected 4)",pc_out);

        pc_next = 32'd8;
        #10;
        $display ( "PC = %0d (expected 8)", pc_out);

        pc_next = 32'd12;
        #10;
        $display("PC = %0d (expected 12)", pc_out);

        rst=1;
        #10;
        $display("PC = %0d (expected 0)", pc_out);

        $finish;
    end
endmodule

pc_tb.vcd
$date
	Mon Jun 01 13:51:54 2026
$end
$version
	Icarus Verilog
$end
$timescale
	1s
$end
$scope module pc_tb $end
$var wire 32 ! pc_out [31:0] $end
$var reg 1 " clk $end
$var reg 32 # pc_next [31:0] $end
$var reg 1 $ rst $end
$scope module uut $end
$var wire 1 " clk $end
$var wire 32 % pc_next [31:0] $end
$var wire 1 $ rst $end
$var reg 32 & pc_out [31:0] $end
$upscope $end
$upscope $end
$enddefinitions $end
#0
$dumpvars
b0 &
b0 %
1$
b0 #
0"
b0 !
$end
#5
1"
#10
0"
b100 #
b100 %
0$
#15
b100 !
b100 &
1"
#20
0"
b1000 #
b1000 %
#25
b1000 !
b1000 &
1"
#30
0"
b1100 #
b1100 %
#35
b1100 !
b1100 &
1"
#40
b0 !
b0 &
0"
1$
