reg_file.v
module reg_file(
    input clk,
    input we,
    input [4:0] raddr1,
    input [4:0] raddr2,
    input [4:0] waddr,
    input [31:0] wdata,
    output [31:0] rdata1,
    output [31:0] rdata2
);

    reg [31:0] registers [31:0];

    integer i;
    initial begin
        for (i = 0; i < 32; i = i + 1)
            registers[i] = 32'b0;
    end

    always @(posedge clk) begin
        if (we && waddr != 5'b0)
            registers[waddr] <= wdata;
    end

    assign rdata1 = registers[raddr1];
    assign rdata2 = registers[raddr2];

endmodule

reg_file_tb.v
module reg_file_tb;

    reg clk;
    reg we;
    reg [4:0] raddr1;
    reg [4:0] raddr2;
    reg [4:0] waddr;
    reg [31:0] wdata;
    wire [31:0] rdata1;
    wire [31:0] rdata2;

    reg_file uut (
        .clk(clk),
        .we(we),
        .raddr1(raddr1),
        .raddr2(raddr2),
        .waddr(waddr),
        .wdata(wdata),
        .rdata1(rdata1),
        .rdata2(rdata2)
    );

    initial clk = 0;
    always #5 clk = ~clk;

    initial begin
        $dumpfile("reg_file_tb.vcd");
        $dumpvars(0, reg_file_tb);

        we = 0;
        raddr1 = 0; raddr2 = 0;
        waddr = 0; wdata = 0;
        #10;

        we = 1;
        waddr = 5'd1;
        wdata = 32'd42;
        #10;

        we = 1;
        waddr = 5'd2;
        wdata = 32'd100;
        #10;

        we = 1;
        waddr = 5'd3;
        wdata = 32'd255;
        #10;

        we = 0;
        raddr1 = 5'd1;
        raddr2 = 5'd2;
        #10;
        $display("Register 1 = %d (expected 42)", rdata1);
        $display("Register 2 = %d (expected 100)", rdata2);

        raddr1 = 5'd3;
        raddr2 = 5'd0;
        #10;
        $display("Register 3 = %d (expected 255)", rdata1);
        $display("Register 0 = %d (expected 0)", rdata2);

        we = 1;
        waddr = 5'd0;
        wdata = 32'd999;
        #10;

        we = 0;
        raddr1 = 5'd0;
        #10;
        $display("Register 0 after write attempt = %d (expected 0)", rdata1);

        $finish;
    end

endmodule

reg_file_tb.vcd
$date
	Tue May 26 09:35:57 2026
$end
$version
	Icarus Verilog
$end
$timescale
	1s
$end
$scope module reg_file_tb $end
$var wire 32 ! rdata2 [31:0] $end
$var wire 32 " rdata1 [31:0] $end
$var reg 1 # clk $end
$var reg 5 $ raddr1 [4:0] $end
$var reg 5 % raddr2 [4:0] $end
$var reg 5 & waddr [4:0] $end
$var reg 32 ' wdata [31:0] $end
$var reg 1 ( we $end
$scope module uut $end
$var wire 1 # clk $end
$var wire 5 ) raddr1 [4:0] $end
$var wire 5 * raddr2 [4:0] $end
$var wire 32 + rdata1 [31:0] $end
$var wire 32 , rdata2 [31:0] $end
$var wire 5 - waddr [4:0] $end
$var wire 32 . wdata [31:0] $end
$var wire 1 ( we $end
$var integer 32 / i [31:0] $end
$upscope $end
$upscope $end
$enddefinitions $end
#0
$dumpvars
b100000 /
b0 .
b0 -
b0 ,
b0 +
b0 *
b0 )
0(
b0 '
b0 &
b0 %
b0 $
0#
b0 "
b0 !
$end
#5
1#
#10
0#
b101010 '
b101010 .
b1 &
b1 -
1(
#15
1#
#20
0#
b1100100 '
b1100100 .
b10 &
b10 -
#25
1#
#30
0#
b11111111 '
b11111111 .
b11 &
b11 -
#35
1#
#40
0#
b1100100 !
b1100100 ,
b10 %
b10 *
b101010 "
b101010 +
b1 $
b1 )
0(
#45
1#
#50
0#
b0 !
b0 ,
b0 %
b0 *
b11111111 "
b11111111 +
b11 $
b11 )
#55
1#
#60
0#
b1111100111 '
b1111100111 .
b0 &
b0 -
1(
#65
1#
#70
0#
b0 "
b0 +
b0 $
b0 )
0(
