vending.v
module vending(
    input  clk,
    input  rst,
    input  coin5,
    input  coin10,
    output reg dispense,
    output reg change
);

    parameter IDLE     = 3'd0;
    parameter S5       = 3'd1;
    parameter S10      = 3'd2;
    parameter S15      = 3'd3;
    parameter DISP     = 3'd4;
    parameter DISP_CHG = 3'd5;

    reg [2:0] current_state, next_state;

    always @(posedge clk or posedge rst) begin
        if (rst)
            current_state <= IDLE;
        else
            current_state <= next_state;
    end

    always @(*) begin
        next_state = current_state;
        dispense   = 0;
        change     = 0;

        case (current_state)
            IDLE: begin
                if (coin5)       next_state = S5;
                else if (coin10) next_state = S10;
            end
            S5: begin
                if (coin5)       next_state = S10;
                else if (coin10) next_state = S15;
            end
            S10: begin
                if (coin5)       next_state = S15;
                else if (coin10) next_state = DISP;
            end
            S15: begin
                if (coin5)       next_state = DISP;
                else if (coin10) next_state = DISP_CHG;
            end
            DISP: begin
                dispense   = 1;
                next_state = IDLE;
            end
            DISP_CHG: begin
                dispense   = 1;
                change     = 1;
                next_state = IDLE;
            end
        endcase
    end

endmodule

vending_tb.v
module vending_tb;

    reg clk;
    reg rst;
    reg coin5;
    reg coin10;
    wire dispense;
    wire change;

    vending uut (
        .clk(clk),
        .rst(rst),
        .coin5(coin5),
        .coin10(coin10),
        .dispense(dispense),
        .change(change)
    );

    initial clk = 0;
    always #5 clk = ~clk;

    integer dispensed;

    initial begin
        $dumpfile("vending_tb.vcd");
        $dumpvars(0, vending_tb);

        rst = 1; coin5 = 0; coin10 = 0;
        #20;
        rst = 0;
        #20;

        dispensed = 0;

        $display("Test 1: Four 5-cent coins");
        coin5 = 1; #10; coin5 = 0; #10;
        coin5 = 1; #10; coin5 = 0; #10;
        coin5 = 1; #10; coin5 = 0; #10;
        coin5 = 1; #10; coin5 = 0;
        @(posedge dispense);
        $display("Dispense triggered - PASS");

        rst = 1; #20; rst = 0; #20;

        $display("Test 2: Two 10-cent coins");
        coin10 = 1; #10; coin10 = 0; #10;
        coin10 = 1; #10; coin10 = 0;
        @(posedge dispense);
        $display("Dispense triggered - PASS");

        rst = 1; #20; rst = 0; #20;

        $display("Test 3: 10 + 5 + 10 cents with change");
        coin10 = 1; #10; coin10 = 0; #10;
        coin5  = 1; #10; coin5  = 0; #10;
        coin10 = 1; #10; coin10 = 0;
        @(posedge dispense);
        $display("Dispense triggered - PASS");
        if (change)
            $display("Change triggered - PASS");
        else
            $display("Change NOT triggered - FAIL");

        #20;
        $finish;
    end

endmodule

vending_tb.vcd
$date
	Wed May 27 12:12:27 2026
$end
$version
	Icarus Verilog
$end
$timescale
	1s
$end
$scope module vending_tb $end
$var wire 1 ! dispense $end
$var wire 1 " change $end
$var reg 1 # clk $end
$var reg 1 $ coin10 $end
$var reg 1 % coin5 $end
$var reg 1 & rst $end
$var integer 32 ' dispensed [31:0] $end
$scope module uut $end
$var wire 1 # clk $end
$var wire 1 $ coin10 $end
$var wire 1 % coin5 $end
$var wire 1 & rst $end
$var reg 1 " change $end
$var reg 3 ( current_state [2:0] $end
$var reg 1 ! dispense $end
$var reg 3 ) next_state [2:0] $end
$upscope $end
$upscope $end
$enddefinitions $end
#0
$dumpvars
b0 )
b0 (
bx '
1&
0%
0$
0#
0"
0!
$end
#5
1#
#10
0#
#15
1#
#20
0#
0&
#25
1#
#30
0#
#35
1#
#40
b1 )
0#
1%
b0 '
#45
b10 )
b1 (
1#
#50
b1 )
0#
0%
#55
1#
#60
b10 )
0#
1%
#65
b11 )
b10 (
1#
#70
b10 )
0#
0%
#75
1#
#80
b11 )
0#
1%
#85
b100 )
b11 (
1#
#90
b11 )
0#
0%
#95
1#
#100
b100 )
0#
1%
#105
b0 )
1!
b100 (
1#
#110
b0 (
1&
0!
b0 )
0#
0%
#115
1#
#120
0#
#125
1#
#130
0#
0&
#135
1#
#140
0#
#145
1#
#150
b10 )
0#
1$
#155
b100 )
b10 (
1#
#160
b10 )
0#
0$
#165
1#
#170
b100 )
0#
1$
#175
b0 )
1!
b100 (
1#
#180
b0 (
1&
0!
b0 )
0#
0$
#185
1#
#190
0#
#195
1#
#200
0#
0&
#205
1#
#210
0#
#215
1#
#220
b10 )
0#
1$
#225
b100 )
b10 (
1#
#230
b10 )
0#
0$
#235
1#
#240
b11 )
0#
1%
#245
b100 )
b11 (
1#
#250
b11 )
0#
0%
#255
1#
#260
b101 )
0#
1$
#265
b0 )
1"
1!
b101 (
1#
#270
1"
1!
b0 )
0#
0$
#275
0"
0!
b0 (
1#
